jikken
