Metadata-Version: 1.0
Name: jikken
Version: 0.2.1
Summary: Minimal Python3 CLI Experiment Manager
Home-page: https://github.com/outcastofmusic/jikken
Author: Agis Oikonomou
Author-email: UNKNOWN
License: BSD
Platform: UNKNOWN
